json_trans/__init__.py
json_trans/index.py
json_trans-0.2.1.dist-info/METADATA
json_trans-0.2.1.dist-info/WHEEL
json_trans-0.2.1.dist-info/RECORD
